{
  "validationRules": [],
  "transactionType": "SOURCE TO TARGET CHILD",
  "tagKeys": "WORK_ORDER_DEBRIEF_-_LOG_USAGE_AGAINST_ESTIMATES;TDM015_2014_05_01_DESC;MANAGE_WO_ESTIMATE_LINES_PAGEHELP;PARTS;LABOR;EXPENSES;TRAVEL;WORK_ORDER;SLA;OPPORTUNITY;GET_PRICE;THIS_RECORD_DOES_NOT_MEET_THE_QUALIFICATION_CRITERIA_FOR_THIS_SFM_TRANSACTION;",
  "syncMobileOption": "Default",
  "status": "Complete",
  "sorting": [],
  "parentProcessNodes": [
    {
      "type": "SOURCE",
      "referenceId": "a0G5g000006qjvaEAA",
      "objectAPIName": "SVMXC__Service_Order__c",
      "enableOnlineSearch": false,
      "allowImages": false,
      "allowAttachments": false
    },
    {
      "type": "TARGET",
      "sourceAPIName": "SVMXC__Service_Order__c",
      "referenceId": "a0G5g000006qjvfEAA",
      "qualificationCriteriaId": "EXPR002",
      "objectLabel": "Work Order",
      "objectAPIName": "SVMXC__Service_Order__c",
      "enableOnlineSearch": false,
      "allowImages": false,
      "allowAttachments": false
    }
  ],
  "pageLayoutDetails": {
    "type": "Header",
    "showAllSections": false,
    "pageHelp": "This SFM transaction is used to create Usage/Consumption lines from existing Estimate lines in a work order.",
    "pageHeader": {
      "sections": [
        {
          "type": "Button",
          "referenceId": "a0c5g00000FJBS6AAP",
          "name": "Get Price",
          "hideSectionTitle": false,
          "events": [
            {
              "type": "Button Click",
              "actionType": "JAVASCRIPT",
              "actionTarget": "a1t5g0000009kghAAA"
            }
          ]
        },
        {
          "type": "Section",
          "sequence": 1,
          "referenceId": "a0c5g00000FJBRmAAP",
          "name": "Work Order",
          "hideSectionTitle": false,
          "elements": [
            {
              "type": "PICKLIST",
              "sequence": 1,
              "row": 1,
              "required": true,
              "readOnly": false,
              "overrideLookupContext": false,
              "lookupConfiguration": {},
              "events": [],
              "eltType": "Field",
              "column": 1,
              "apiName": "SVMXC__Order_Status__c"
            },
            {
              "type": "PICKLIST",
              "sequence": 2,
              "row": 1,
              "required": false,
              "readOnly": false,
              "overrideLookupContext": false,
              "lookupConfiguration": {},
              "events": [],
              "eltType": "Field",
              "column": 2,
              "apiName": "SVMXC__Billing_Type__c"
            },
            {
              "type": "TEXTAREA",
              "sequence": 3,
              "row": 2,
              "required": false,
              "readOnly": false,
              "overrideLookupContext": false,
              "lookupConfiguration": {},
              "events": [],
              "eltType": "Field",
              "column": 1,
              "apiName": "SVMXC__Work_Performed__c"
            },
            {
              "type": "TEXTAREA",
              "sequence": 4,
              "row": 2,
              "required": false,
              "readOnly": false,
              "overrideLookupContext": false,
              "lookupConfiguration": {},
              "events": [],
              "eltType": "Field",
              "column": 2,
              "apiName": "SVMXC__Customer_Failure_Feedback__c"
            },
            {
              "type": "PICKLIST",
              "sequence": 5,
              "row": 3,
              "required": false,
              "readOnly": false,
              "overrideLookupContext": false,
              "lookupConfiguration": {},
              "events": [],
              "eltType": "Field",
              "column": 1,
              "apiName": "SVMXC__Symptom__c"
            },
            {
              "type": "PICKLIST",
              "sequence": 6,
              "row": 3,
              "required": false,
              "readOnly": false,
              "overrideLookupContext": false,
              "lookupConfiguration": {},
              "events": [],
              "eltType": "Field",
              "column": 2,
              "apiName": "SVMXC__Root_Cause__c"
            },
            {
              "type": "PICKLIST",
              "sequence": 7,
              "row": 4,
              "required": false,
              "readOnly": false,
              "overrideLookupContext": false,
              "lookupConfiguration": {},
              "events": [],
              "eltType": "Field",
              "column": 1,
              "apiName": "SVMXC__Failed_Assembly__c"
            },
            {
              "type": "PICKLIST",
              "sequence": 8,
              "row": 4,
              "required": false,
              "readOnly": false,
              "overrideLookupContext": false,
              "lookupConfiguration": {},
              "events": [],
              "eltType": "Field",
              "column": 2,
              "apiName": "SVMXC__How_Fixed__c"
            }
          ],
          "columns": 2
        },
        {
          "type": "Section",
          "sequence": 2,
          "referenceId": "a0c5g00000FJBRnAAP",
          "name": "SLA",
          "hideSectionTitle": false,
          "elements": [
            {
              "type": "PICKLIST",
              "sequence": 1,
              "row": 1,
              "required": false,
              "readOnly": false,
              "overrideLookupContext": false,
              "lookupConfiguration": {},
              "events": [],
              "eltType": "Field",
              "column": 1,
              "apiName": "SVMXC__Dispatch_Response__c"
            },
            {
              "type": "DATETIME",
              "sequence": 2,
              "row": 1,
              "required": false,
              "readOnly": false,
              "overrideLookupContext": false,
              "lookupConfiguration": {},
              "events": [],
              "eltType": "Field",
              "column": 2,
              "apiName": "SVMXC__Actual_Onsite_Response__c"
            },
            {
              "type": "DATETIME",
              "sequence": 3,
              "row": 2,
              "required": false,
              "readOnly": false,
              "overrideLookupContext": false,
              "lookupConfiguration": {},
              "events": [],
              "eltType": "Field",
              "column": 1,
              "apiName": "SVMXC__Actual_Resolution__c"
            },
            {
              "type": "DATETIME",
              "sequence": 4,
              "row": 2,
              "required": false,
              "readOnly": false,
              "overrideLookupContext": false,
              "lookupConfiguration": {},
              "events": [],
              "eltType": "Field",
              "column": 2,
              "apiName": "SVMXC__Actual_Restoration__c"
            }
          ],
          "columns": 2
        },
        {
          "type": "Section",
          "sequence": 3,
          "referenceId": "a0c5g00000FJBRoAAP",
          "name": "Opportunity",
          "hideSectionTitle": false,
          "elements": [
            {
              "type": "BOOLEAN",
              "sequence": 1,
              "row": 1,
              "required": false,
              "readOnly": false,
              "overrideLookupContext": false,
              "lookupConfiguration": {},
              "events": [],
              "eltType": "Field",
              "column": 1,
              "apiName": "Opportunity_Found__c"
            },
            {
              "type": "TEXTAREA",
              "sequence": 2,
              "row": 2,
              "required": false,
              "readOnly": false,
              "overrideLookupContext": false,
              "lookupConfiguration": {},
              "events": [],
              "eltType": "Field",
              "column": 1,
              "apiName": "Opportunity_Notes__c"
            }
          ],
          "columns": 1
        },
        {
          "type": "Detail",
          "sequence": 1,
          "referenceId": "a0d5g000003fLAzAAM",
          "objectAlias": "Parts",
          "name": "Parts",
          "childAPIName": "SVMXC__Service_Order_Line__c",
          "allowZeroLines": "Allow"
        },
        {
          "type": "Detail",
          "sequence": 2,
          "referenceId": "a0d5g000003fLB0AAM",
          "objectAlias": "Labor",
          "name": "Labor",
          "childAPIName": "SVMXC__Service_Order_Line__c",
          "allowZeroLines": "Allow"
        },
        {
          "type": "Detail",
          "sequence": 3,
          "referenceId": "a0d5g000003fLB1AAM",
          "objectAlias": "Expense",
          "name": "Expenses",
          "childAPIName": "SVMXC__Service_Order_Line__c",
          "allowZeroLines": "Allow"
        },
        {
          "type": "Detail",
          "sequence": 4,
          "referenceId": "a0d5g000003fLB2AAM",
          "objectAlias": "Travel",
          "name": "Travel",
          "columns": 2,
          "childAPIName": "SVMXC__Service_Order_Line__c"
        }
      ],
      "objectAPIName": "SVMXC__Service_Order__c"
    },
    "objectAPIName": "SVMXC__Service_Order__c",
    "name": "Manage WO Estimate Lines",
    "lines": [
      {
        "sourceControllerReferenceField": "SVMXC__Service_Order__c",
        "sequence": 1,
        "referenceId": "a0d5g000003fLAzAAM",
        "objectAlias": "Parts",
        "name": "Parts",
        "hideEmptySection": false,
        "elements": [
          {
            "type": "REFERENCE",
            "sequence": 1,
            "row": 0,
            "required": true,
            "referenceTo": "Product2",
            "referenceNameField": "Name",
            "readOnly": false,
            "overrideLookupContext": false,
            "lookupContextSource": "CURRENT_RECORD",
            "lookupConfiguration": {
              "name": "SVMXSTD: Product Lookup",
              "isStandard": true,
              "description": "Pre-configured standard lookup for Product object",
              "lookupObject": "Product2",
              "lookupFilter": {
                "sourceObject": "Product2",
                "expressionsList": [
                  {
                    "sourceField": "Name",
                    "sequence": 1,
                    "actionType": "Set Value"
                  },
                  {
                    "sourceField": "Name",
                    "sequence": 1,
                    "actionType": "Set Value"
                  },
                  {
                    "sourceField": "Name",
                    "sequence": 1,
                    "actionType": "Set Value"
                  },
                  {
                    "sourceField": "ProductCode",
                    "sequence": 2,
                    "actionType": "Set Value"
                  },
                  {
                    "sourceField": "ProductCode",
                    "sequence": 2,
                    "actionType": "Set Value"
                  },
                  {
                    "sourceField": "ProductCode",
                    "sequence": 2,
                    "actionType": "Set Value"
                  },
                  {
                    "sourceField": "Family",
                    "sequence": 3,
                    "actionType": "Set Value"
                  },
                  {
                    "sourceField": "Family",
                    "sequence": 3,
                    "actionType": "Set Value"
                  },
                  {
                    "sourceField": "Family",
                    "sequence": 3,
                    "actionType": "Set Value"
                  }
                ],
                "defaultOn": false,
                "allowOverride": false
              },
              "lkpRecords": 10,
              "isDefault": true,
              "defaultColumn": "Name",
              "advancedFilters": [
                {
                  "sourceObject": "SVMXC__Product_Stock__c",
                  "expressionsList": [
                    {
                      "value": "Available",
                      "sourceField": "SVMXC__Status__c",
                      "sequence": 1,
                      "parameterType": "Value",
                      "operator": "eq",
                      "operand": "Available",
                      "actionType": "Set Value"
                    },
                    {
                      "value": "0",
                      "sourceField": "SVMXC__Available_Qty__c",
                      "sequence": 2,
                      "parameterType": "Value",
                      "operator": "gt",
                      "operand": "0",
                      "actionType": "Set Value"
                    },
                    {
                      "value": "User Trunk",
                      "sourceField": "SVMXC__Location__c",
                      "sequence": 3,
                      "parameterType": "Constant",
                      "operator": "eq",
                      "operand": "User Trunk",
                      "actionType": "Set Value"
                    }
                  ],
                  "defaultOn": false,
                  "allowOverride": true
                }
              ]
            },
            "lookupConfigName": "SVMXSTD: Product Lookup",
            "events": [],
            "eltType": "Field",
            "column": 1,
            "apiName": "SVMXC__Product__c"
          },
          {
            "type": "DOUBLE",
            "sequence": 2,
            "row": 0,
            "required": true,
            "readOnly": false,
            "overrideLookupContext": false,
            "lookupConfiguration": {},
            "events": [],
            "eltType": "Field",
            "column": 2,
            "apiName": "SVMXC__Actual_Quantity2__c"
          },
          {
            "type": "CURRENCY",
            "sequence": 3,
            "row": 0,
            "required": false,
            "readOnly": false,
            "overrideLookupContext": false,
            "lookupConfiguration": {},
            "events": [],
            "eltType": "Field",
            "column": 3,
            "apiName": "SVMXC__Actual_Price2__c"
          },
          {
            "type": "TEXTAREA",
            "sequence": 4,
            "row": 0,
            "required": false,
            "readOnly": false,
            "overrideLookupContext": false,
            "lookupConfiguration": {},
            "events": [],
            "eltType": "Field",
            "column": 4,
            "apiName": "SVMXC__Work_Description__c"
          },
          {
            "type": "BOOLEAN",
            "sequence": 5,
            "row": 0,
            "required": false,
            "readOnly": false,
            "overrideLookupContext": false,
            "lookupConfiguration": {},
            "events": [],
            "eltType": "Field",
            "column": 5,
            "apiName": "SVMXC__Is_Billable__c"
          }
        ],
        "childAPIName": "SVMXC__Service_Order_Line__c",
        "allowZeroLines": "Allow"
      },
      {
        "sourceControllerReferenceField": "SVMXC__Service_Order__c",
        "sequence": 2,
        "referenceId": "a0d5g000003fLB0AAM",
        "objectAlias": "Labor",
        "name": "Labor",
        "hideEmptySection": false,
        "elements": [
          {
            "type": "PICKLIST",
            "sequence": 1,
            "row": 0,
            "required": false,
            "readOnly": false,
            "overrideLookupContext": false,
            "lookupConfiguration": {},
            "events": [],
            "eltType": "Field",
            "column": 1,
            "apiName": "SVMXC__Activity_Type__c"
          },
          {
            "type": "DOUBLE",
            "sequence": 2,
            "row": 0,
            "required": false,
            "readOnly": false,
            "overrideLookupContext": false,
            "lookupConfiguration": {},
            "events": [],
            "eltType": "Field",
            "column": 2,
            "apiName": "SVMXC__Actual_Quantity2__c"
          },
          {
            "type": "DATETIME",
            "sequence": 3,
            "row": 0,
            "required": false,
            "readOnly": false,
            "overrideLookupContext": false,
            "lookupConfiguration": {},
            "events": [],
            "eltType": "Field",
            "column": 3,
            "apiName": "SVMXC__Start_Date_and_Time__c"
          },
          {
            "type": "DATETIME",
            "sequence": 4,
            "row": 0,
            "required": false,
            "readOnly": false,
            "overrideLookupContext": false,
            "lookupConfiguration": {},
            "events": [],
            "eltType": "Field",
            "column": 4,
            "apiName": "SVMXC__End_Date_and_Time__c"
          },
          {
            "type": "CURRENCY",
            "sequence": 5,
            "row": 0,
            "required": false,
            "readOnly": false,
            "overrideLookupContext": false,
            "lookupConfiguration": {},
            "events": [],
            "eltType": "Field",
            "column": 5,
            "apiName": "SVMXC__Actual_Price2__c"
          },
          {
            "type": "PERCENT",
            "sequence": 6,
            "row": 0,
            "required": false,
            "readOnly": false,
            "overrideLookupContext": false,
            "lookupConfiguration": {},
            "events": [],
            "eltType": "Field",
            "column": 6,
            "apiName": "SVMXC__Discount__c"
          },
          {
            "type": "TEXTAREA",
            "sequence": 7,
            "row": 0,
            "required": false,
            "readOnly": false,
            "overrideLookupContext": false,
            "lookupConfiguration": {},
            "events": [],
            "eltType": "Field",
            "column": 7,
            "apiName": "SVMXC__Work_Description__c"
          },
          {
            "type": "BOOLEAN",
            "sequence": 8,
            "row": 0,
            "required": false,
            "readOnly": false,
            "overrideLookupContext": false,
            "lookupConfiguration": {},
            "events": [],
            "eltType": "Field",
            "column": 8,
            "apiName": "SVMXC__Is_Billable__c"
          },
          {
            "type": "REFERENCE",
            "sequence": 9,
            "row": 0,
            "required": true,
            "referenceTo": "SVMXC__Service_Group_Members__c",
            "referenceNameField": "Name",
            "readOnly": false,
            "overrideLookupContext": false,
            "lookupContextSource": "CURRENT_RECORD",
            "lookupConfiguration": {},
            "events": [],
            "eltType": "Field",
            "column": 9,
            "apiName": "SVMXC__Group_Member__c"
          }
        ],
        "childAPIName": "SVMXC__Service_Order_Line__c",
        "allowZeroLines": "Allow"
      },
      {
        "sourceControllerReferenceField": "SVMXC__Service_Order__c",
        "sequence": 3,
        "referenceId": "a0d5g000003fLB1AAM",
        "objectAlias": "Expense",
        "name": "Expenses",
        "hideEmptySection": false,
        "elements": [
          {
            "type": "PICKLIST",
            "sequence": 1,
            "row": 0,
            "required": false,
            "readOnly": false,
            "overrideLookupContext": false,
            "lookupConfiguration": {},
            "events": [],
            "eltType": "Field",
            "column": 1,
            "apiName": "SVMXC__Expense_Type__c"
          },
          {
            "type": "DOUBLE",
            "sequence": 2,
            "row": 0,
            "required": false,
            "readOnly": false,
            "overrideLookupContext": false,
            "lookupConfiguration": {},
            "events": [],
            "eltType": "Field",
            "column": 2,
            "apiName": "SVMXC__Actual_Quantity2__c"
          },
          {
            "type": "CURRENCY",
            "sequence": 3,
            "row": 0,
            "required": false,
            "readOnly": false,
            "overrideLookupContext": false,
            "lookupConfiguration": {},
            "events": [],
            "eltType": "Field",
            "column": 3,
            "apiName": "SVMXC__Actual_Price2__c"
          },
          {
            "type": "TEXTAREA",
            "sequence": 4,
            "row": 0,
            "required": false,
            "readOnly": false,
            "overrideLookupContext": false,
            "lookupConfiguration": {},
            "events": [],
            "eltType": "Field",
            "column": 4,
            "apiName": "SVMXC__Work_Description__c"
          },
          {
            "type": "BOOLEAN",
            "sequence": 5,
            "row": 0,
            "required": false,
            "readOnly": false,
            "overrideLookupContext": false,
            "lookupConfiguration": {},
            "events": [],
            "eltType": "Field",
            "column": 5,
            "apiName": "SVMXC__Is_Billable__c"
          }
        ],
        "childAPIName": "SVMXC__Service_Order_Line__c",
        "allowZeroLines": "Allow"
      },
      {
        "sourceControllerReferenceField": "SVMXC__Service_Order__c",
        "sequence": 4,
        "referenceId": "a0d5g000003fLB2AAM",
        "objectAlias": "Travel",
        "name": "Travel",
        "hideEmptySection": false,
        "elements": [
          {
            "type": "DATETIME",
            "sequence": 1,
            "row": 0,
            "required": false,
            "readOnly": false,
            "overrideLookupContext": false,
            "lookupConfiguration": {},
            "events": [],
            "eltType": "Field",
            "column": 1,
            "apiName": "SVMXC__Start_Date_and_Time__c"
          },
          {
            "type": "DATETIME",
            "sequence": 2,
            "row": 0,
            "required": false,
            "readOnly": false,
            "overrideLookupContext": false,
            "lookupConfiguration": {},
            "events": [],
            "eltType": "Field",
            "column": 2,
            "apiName": "SVMXC__End_Date_and_Time__c"
          },
          {
            "type": "BOOLEAN",
            "sequence": 3,
            "row": 0,
            "required": false,
            "readOnly": false,
            "overrideLookupContext": false,
            "lookupConfiguration": {},
            "events": [],
            "eltType": "Field",
            "column": 3,
            "apiName": "SVMXC__Use_Price_From_Pricebook__c"
          },
          {
            "type": "DOUBLE",
            "sequence": 4,
            "row": 0,
            "required": false,
            "readOnly": false,
            "overrideLookupContext": false,
            "lookupConfiguration": {},
            "events": [],
            "eltType": "Field",
            "column": 4,
            "apiName": "SVMXC__Actual_Quantity2__c"
          },
          {
            "type": "CURRENCY",
            "sequence": 5,
            "row": 0,
            "required": false,
            "readOnly": false,
            "overrideLookupContext": false,
            "lookupConfiguration": {},
            "events": [],
            "eltType": "Field",
            "column": 5,
            "apiName": "SVMXC__Actual_Price2__c"
          },
          {
            "type": "PERCENT",
            "sequence": 6,
            "row": 0,
            "required": false,
            "readOnly": false,
            "overrideLookupContext": false,
            "lookupConfiguration": {},
            "events": [],
            "eltType": "Field",
            "column": 6,
            "apiName": "SVMXC__Covered__c"
          },
          {
            "type": "TEXTAREA",
            "sequence": 7,
            "row": 0,
            "required": false,
            "readOnly": false,
            "overrideLookupContext": false,
            "lookupConfiguration": {},
            "events": [],
            "eltType": "Field",
            "column": 7,
            "apiName": "SVMXC__Work_Description__c"
          },
          {
            "type": "BOOLEAN",
            "sequence": 8,
            "row": 0,
            "required": false,
            "readOnly": false,
            "overrideLookupContext": false,
            "lookupConfiguration": {},
            "events": [],
            "eltType": "Field",
            "column": 8,
            "apiName": "SVMXC__Is_Billable__c"
          },
          {
            "type": "DOUBLE",
            "sequence": 9,
            "row": 0,
            "required": false,
            "readOnly": false,
            "overrideLookupContext": false,
            "lookupConfiguration": {},
            "events": [],
            "eltType": "Field",
            "column": 9,
            "apiName": "SVMXC__Billable_Quantity__c"
          },
          {
            "type": "CURRENCY",
            "sequence": 10,
            "row": 0,
            "required": false,
            "readOnly": false,
            "overrideLookupContext": false,
            "lookupConfiguration": {},
            "events": [],
            "eltType": "Field",
            "column": 10,
            "apiName": "SVMXC__Billable_Line_Price__c"
          }
        ],
        "columns": 2,
        "childAPIName": "SVMXC__Service_Order_Line__c"
      }
    ],
    "isStandard": false,
    "hideSave": false,
    "hideQuickSave": true,
    "helpUrl": "http://userdocs.servicemax.com:8080/ServiceMaxHelp/Summer11/en_us/svmx_redirector.htm?uid=APP19_11",
    "events": [],
    "dependencyExist": true
  },
  "name": "Work Order Debrief - Log Usage against Estimates",
  "linkedProcesses": [],
  "isStandard": false,
  "formulas": [],
  "developerName": "TDM015_2014_05_01",
  "description": "Work Order Debrief - Log Usage against Estimates",
  "childProcessNodes": [
    {
      "type": "SOURCECHILD",
      "sequence": 1,
      "referenceId": "a0G5g000006qjvbEAA",
      "parentColumnAPIName": "SVMXC__Service_Order__c",
      "objectAPIName": "SVMXC__Service_Order_Line__c",
      "nodeAPIName": "SVMXC__Service_Order__c",
      "enableOnlineSearch": false,
      "allowImages": false,
      "allowAttachments": false
    },
    {
      "type": "SOURCECHILD",
      "sequence": 2,
      "referenceId": "a0G5g000006qjvcEAA",
      "parentColumnAPIName": "SVMXC__Service_Order__c",
      "objectAPIName": "SVMXC__Service_Order_Line__c",
      "nodeAPIName": "SVMXC__Service_Order__c",
      "enableOnlineSearch": false,
      "allowImages": false,
      "allowAttachments": false
    },
    {
      "type": "SOURCECHILD",
      "sequence": 3,
      "referenceId": "a0G5g000006qjvdEAA",
      "parentColumnAPIName": "SVMXC__Service_Order__c",
      "objectAPIName": "SVMXC__Service_Order_Line__c",
      "nodeAPIName": "SVMXC__Service_Order__c",
      "enableOnlineSearch": false,
      "allowImages": false,
      "allowAttachments": false
    },
    {
      "type": "SOURCECHILD",
      "sequence": 4,
      "referenceId": "a0G5g000006qjveEAA",
      "parentColumnAPIName": "SVMXC__Service_Order__c",
      "objectAPIName": "SVMXC__Service_Order_Line__c",
      "nodeAPIName": "SVMXC__Service_Order__c",
      "enableOnlineSearch": false,
      "allowImages": false,
      "allowAttachments": false
    },
    {
      "type": "TARGETCHILD",
      "sourceAPIName": "SVMXC__Service_Order_Line__c",
      "sequence": 1,
      "referenceId": "a0G5g000006qjvgEAA",
      "qualificationCriteriaId": "SVMXSTD:_Parts_Estimate_Lines_Only_RTText",
      "parentColumnAPIName": "SVMXC__Service_Order__c",
      "objectLabel": "Parts",
      "objectAPIName": "SVMXC__Service_Order_Line__c",
      "nodeAPIName": "SVMXC__Service_Order__c",
      "mappingId": "MAP031V",
      "enableOnlineSearch": false,
      "allowImages": false,
      "allowAttachments": false
    },
    {
      "type": "TARGETCHILD",
      "sourceAPIName": "SVMXC__Service_Order_Line__c",
      "sequence": 2,
      "referenceId": "a0G5g000006qjvhEAA",
      "qualificationCriteriaId": "SVMXSTD:_Labor_Estimate_Lines_Only_RTText",
      "parentColumnAPIName": "SVMXC__Service_Order__c",
      "objectLabel": "Labor",
      "objectAPIName": "SVMXC__Service_Order_Line__c",
      "nodeAPIName": "SVMXC__Service_Order__c",
      "mappingId": "MAP032V",
      "enableOnlineSearch": false,
      "allowImages": false,
      "allowAttachments": false
    },
    {
      "type": "TARGETCHILD",
      "sourceAPIName": "SVMXC__Service_Order_Line__c",
      "sequence": 3,
      "referenceId": "a0G5g000006qjviEAA",
      "qualificationCriteriaId": "SVMXSTD:_Expense_Estimate_Lines_Only_RTText",
      "parentColumnAPIName": "SVMXC__Service_Order__c",
      "objectLabel": "Expense",
      "objectAPIName": "SVMXC__Service_Order_Line__c",
      "nodeAPIName": "SVMXC__Service_Order__c",
      "mappingId": "MAP033V",
      "enableOnlineSearch": false,
      "allowImages": false,
      "allowAttachments": false
    },
    {
      "type": "TARGETCHILD",
      "sourceAPIName": "SVMXC__Service_Order_Line__c",
      "sequence": 4,
      "referenceId": "a0G5g000006qjvjEAA",
      "qualificationCriteriaId": "EXPR064",
      "parentColumnAPIName": "SVMXC__Service_Order__c",
      "objectLabel": "Travel",
      "objectAPIName": "SVMXC__Service_Order_Line__c",
      "nodeAPIName": "SVMXC__Service_Order__c",
      "enableOnlineSearch": false,
      "allowImages": false,
      "allowAttachments": false
    }
  ]
}