{
  "wizardSteps": [
    {
      "wizardDeveloperName": "Intro_WorkOrder",
      "sequence": 1,
      "selectTemplateAtRuntime": false,
      "processId": "TDM018",
      "processDeveloperName": "TDM018",
      "name": "Request Parts",
      "modeOfExecution": "Interactive",
      "isStandard": false,
      "handover": false,
      "expertiseMatchEnabled": false,
      "enableConfirmationDialog": false,
      "description": "This SFM transaction is used to create or edit Parts Request lines in a work order",
      "active": false,
      "actionType": "SFM"
    },
    {
      "wizardDeveloperName": "Intro_WorkOrder",
      "sequence": 2,
      "selectTemplateAtRuntime": false,
      "processId": "OTH062",
      "processDeveloperName": "OTH062",
      "name": "Dispatch Technician",
      "modeOfExecution": "Interactive",
      "isStandard": false,
      "handover": false,
      "expertiseMatchEnabled": false,
      "enableConfirmationDialog": false,
      "description": "Dispatch Technician (DC HTML)",
      "active": false,
      "actionType": "OTHERS"
    },
    {
      "wizardDeveloperName": "Intro_WorkOrder",
      "sequence": 3,
      "selectTemplateAtRuntime": false,
      "processId": "Accept_Work_Order",
      "processDeveloperName": "Accept_Work_Order",
      "name": "Accept Work Order",
      "modeOfExecution": "Interactive",
      "isStandard": false,
      "handover": false,
      "expressionDeveloperName": "Technician_Assigned",
      "expression": "Technician_Assigned",
      "expertiseMatchEnabled": false,
      "enableConfirmationDialog": false,
      "description": "Dispatch Response to Accept Assignment",
      "active": false,
      "actionType": "SFM"
    },
    {
      "wizardDeveloperName": "Intro_WorkOrder",
      "sequence": 4,
      "selectTemplateAtRuntime": false,
      "processId": "Work_Order_Debrief_Intro",
      "processDeveloperName": "Work_Order_Debrief_Intro",
      "name": "Work Order Debrief",
      "modeOfExecution": "Interactive",
      "isStandard": false,
      "handover": false,
      "expressionDeveloperName": "Technician_Assigned",
      "expression": "Technician_Assigned",
      "expertiseMatchEnabled": false,
      "enableConfirmationDialog": false,
      "description": "This SFM transaction is used to enter parts, labor and expenses used in a work order. This is typically used at the end of the resolution, before the work order is closed.",
      "active": false,
      "actionType": "SFM"
    },
    {
      "wizardDeveloperName": "Intro_WorkOrder",
      "sequence": 5,
      "selectTemplateAtRuntime": true,
      "name": "Checklists",
      "modeOfExecution": "Interactive",
      "isStandard": false,
      "handover": false,
      "expressionDeveloperName": "Technician_Assigned",
      "expression": "Technician_Assigned",
      "expertiseMatchEnabled": false,
      "enableConfirmationDialog": false,
      "description": "site safety Checklist",
      "active": false,
      "actionType": "CHECKLIST"
    },
    {
      "wizardDeveloperName": "Intro_WorkOrder",
      "sequence": 6,
      "selectTemplateAtRuntime": false,
      "processId": "WO_ServiceReport_001_Usage_external",
      "processDeveloperName": "WO_ServiceReport_001_Usage_external",
      "name": "Generate Service Report",
      "modeOfExecution": "Interactive",
      "isStandard": false,
      "handover": false,
      "expressionDeveloperName": "Technician_Assigned",
      "expression": "Technician_Assigned",
      "expertiseMatchEnabled": false,
      "enableConfirmationDialog": false,
      "description": "Work Order Service Report\nCustomer and Technician Signature, No Parts Pricing",
      "active": false,
      "actionType": "OUTPUT_DOCUMENT"
    }
  ],
  "wizardAccess": [
    {
      "wizardDeveloperName": "Intro_WorkOrder",
      "accessConfigurationProfile": "Intro Profile"
    }
  ],
  "status": "Complete",
  "objectName": "SVMXC__Service_Order__c",
  "name": "Work Order Management",
  "isStandard": false,
  "developerName": "Intro_WorkOrder",
  "active": true
}